agent_marketplace_sdk/__init__.py
agent_marketplace_sdk/async_client.py
agent_marketplace_sdk/auth.py
agent_marketplace_sdk/client.py
agent_marketplace_sdk/config.py
agent_marketplace_sdk/exceptions.py
agent_marketplace_sdk/py.typed
agent_marketplace_sdk/models/__init__.py
agent_marketplace_sdk/models/agent.py
agent_marketplace_sdk/models/analytics.py
agent_marketplace_sdk/models/category.py
agent_marketplace_sdk/models/review.py
agent_marketplace_sdk/models/user.py
agent_marketplace_sdk/resources/__init__.py
agent_marketplace_sdk/resources/agents.py
agent_marketplace_sdk/resources/analytics.py
agent_marketplace_sdk/resources/categories.py
agent_marketplace_sdk/resources/reviews.py
agent_marketplace_sdk/resources/search.py
agent_marketplace_sdk/resources/users.py
agent_marketplace_sdk/utils/__init__.py
agent_marketplace_sdk/utils/download.py
agent_marketplace_sdk/utils/packaging.py
agent_marketplace_sdk/utils/upload.py
agent_marketplace_sdk/utils/validation.py
agent_marketplace_ld_sdk-0.1.1.dist-info/METADATA
agent_marketplace_ld_sdk-0.1.1.dist-info/WHEEL
agent_marketplace_ld_sdk-0.1.1.dist-info/licenses/LICENSE
agent_marketplace_ld_sdk-0.1.1.dist-info/RECORD
