Metadata-Version: 2.4
Name: agent-marketplace-ld-sdk
Version: 0.1.1
Summary: Official Python SDK for Agent Marketplace. Discover, install, and publish AI agents programmatically.
Project-URL: Homepage, https://github.com/kmcallorum/agent-marketplace-ld-sdk
Project-URL: Documentation, https://github.com/kmcallorum/agent-marketplace-ld-sdk#readme
Project-URL: Repository, https://github.com/kmcallorum/agent-marketplace-ld-sdk
Project-URL: Issues, https://github.com/kmcallorum/agent-marketplace-ld-sdk/issues
Author-email: Kevin McAllorum <kmcallorum@example.com>
License-Expression: MIT
License-File: LICENSE
Keywords: agent-discovery,agent-installation,agent-marketplace,api-client,async,client,httpx,pydantic,pytest-agents,python,sdk,type-safe
Classifier: Development Status :: 4 - Beta
Classifier: Intended Audience :: Developers
Classifier: License :: OSI Approved :: MIT License
Classifier: Operating System :: OS Independent
Classifier: Programming Language :: Python :: 3
Classifier: Programming Language :: Python :: 3.11
Classifier: Programming Language :: Python :: 3.12
Classifier: Typing :: Typed
Requires-Python: >=3.11
Requires-Dist: httpx>=0.26.0
Requires-Dist: pydantic>=2.0.0
Requires-Dist: python-dateutil>=2.8.0
Requires-Dist: typing-extensions>=4.9.0
Provides-Extra: dev
Requires-Dist: faker>=22.0.0; extra == 'dev'
Requires-Dist: mypy>=1.8.0; extra == 'dev'
Requires-Dist: pytest-asyncio>=0.23.0; extra == 'dev'
Requires-Dist: pytest-cov>=4.1.0; extra == 'dev'
Requires-Dist: pytest-mock>=3.12.0; extra == 'dev'
Requires-Dist: pytest>=8.0.0; extra == 'dev'
Requires-Dist: respx>=0.20.0; extra == 'dev'
Requires-Dist: ruff>=0.1.0; extra == 'dev'
Requires-Dist: types-python-dateutil>=2.8.0; extra == 'dev'
